.gitignore
HISTORY.txt
MANIFEST.in
README.rst
setup.py
git_svn_helpers.egg-info/PKG-INFO
git_svn_helpers.egg-info/SOURCES.txt
git_svn_helpers.egg-info/dependency_links.txt
git_svn_helpers.egg-info/entry_points.txt
git_svn_helpers.egg-info/not-zip-safe
git_svn_helpers.egg-info/requires.txt
git_svn_helpers.egg-info/top_level.txt
gitsvnhelpers/__init__.py
gitsvnhelpers/commands.py
gitsvnhelpers/config.py
gitsvnhelpers/gitify.py
gitsvnhelpers/testing.py
gitsvnhelpers/utils.py
gitsvnhelpers/tests/__init__.py
gitsvnhelpers/tests/test_doctests.py
gitsvnhelpers/tests/test_git.py
gitsvnhelpers/tests/test_gitify.txt
gitsvnhelpers/tests/test_gitify_fetch.txt
gitsvnhelpers/tests/test_gitify_up.txt
gitsvnhelpers/tests/test_setup.py
gitsvnhelpers/tests/test_svn_switch.txt
gitsvnhelpers/tests/test_symlink_migration.txt
misc/git_hooks_update
misc/setupgitrepo