Metadata-Version: 1.0
Name: git-svn-helpers
Version: 0.9
Summary: Command-line tools to make git-svn simple
Home-page: http://github.com/collective/git-svn-helpers
Author: Tom Lazar
Author-email: tom@tomster.org
License: UNKNOWN
Keywords: git svn
Platform: UNKNOWN
Classifier: Development Status :: 4 - Beta
Classifier: Environment :: Console
Classifier: Intended Audience :: Developers
Classifier: Topic :: Software Development :: Version Control
Classifier: Programming Language :: Python
Classifier: License :: OSI Approved :: BSD License
